cavaliercontours/__init__.py
cavaliercontours/cavaliercontours.py
cavaliercontours/lib/libCavalierContours.so
cavaliercontours_python-0.0.1.dist-info/LICENSE
cavaliercontours_python-0.0.1.dist-info/METADATA
cavaliercontours_python-0.0.1.dist-info/WHEEL
cavaliercontours_python-0.0.1.dist-info/top_level.txt
cavaliercontours_python-0.0.1.dist-info/RECORD
