Metadata-Version: 2.1
Name: cavaliercontours-python
Version: 0.0.1
Summary: Python binding to the CavalierContours C++ library
Home-page: https://github.com/proto3/cavaliercontours-python
Author: Lucas Felix
Author-email: lucas.felix0738@gmail.com
License: UNKNOWN
Platform: UNKNOWN
Classifier: Programming Language :: Python :: 3
Classifier: License :: OSI Approved :: MIT License
Classifier: Operating System :: POSIX :: Linux
Requires-Python: >=3.6
Requires-Dist: numpy
